fut/EAHashingAlgorithm.py
fut/__init__.py
fut/api.py
fut/config.py
fut/core.py
fut/exceptions.py
fut/log.py
fut/urls.py
fut-0.2.9.dist-info/DESCRIPTION.rst
fut-0.2.9.dist-info/METADATA
fut-0.2.9.dist-info/RECORD
fut-0.2.9.dist-info/WHEEL
fut-0.2.9.dist-info/metadata.json
fut-0.2.9.dist-info/top_level.txt
fut14/EAHashingAlgorithm.py
fut14/__init__.py
fut14/api.py
fut14/config.py
fut14/core.py
fut14/exceptions.py
fut14/log.py
fut14/urls.py
