Metadata-Version: 2.0
Name: fut
Version: 0.2.9
Summary: fut is a simple library for managing Fifa Ultimate Team.
Home-page: https://github.com/oczkers/fut
Author: Piotr Staroszczyk
Author-email: piotr.staroszczyk@get24.org
License: GNU GPL v3
Download-URL: https://github.com/oczkers/fut/releases
Keywords: fut fifa ultimate team ut pc xbox android ios 360 ps3 playstation
Platform: any
Classifier: Development Status :: 3 - Alpha
Classifier: Intended Audience :: Developers
Classifier: Natural Language :: English
Classifier: License :: OSI Approved :: GNU General Public License v3 or later (GPLv3+)
Classifier: Programming Language :: Python
Classifier: Programming Language :: Python :: 2.6
Classifier: Programming Language :: Python :: 2.7
Classifier: Programming Language :: Python :: 3
Classifier: Programming Language :: Python :: 3.3
Classifier: Programming Language :: Python :: 3.4
Classifier: Programming Language :: Python :: 3.5
Classifier: Programming Language :: Python :: Implementation :: PyPy
Classifier: Topic :: Internet :: WWW/HTTP :: Site Management
Classifier: Topic :: Software Development :: Libraries :: Python Modules
Requires-Dist: requests (>=2.2.1)
Requires-Dist: xmltodict
